irp/__init__.py
irp-0.6.0.dist-info/DESCRIPTION.rst
irp-0.6.0.dist-info/METADATA
irp-0.6.0.dist-info/RECORD
irp-0.6.0.dist-info/WHEEL
irp-0.6.0.dist-info/metadata.json
irp-0.6.0.dist-info/top_level.txt
