Metadata-Version: 2.0
Name: irp
Version: 0.6.0
Summary: Gets possible airports for city names!
Home-page: https://github.com/aerupt/irp
Author: Lasse Schuirmann
Author-email: lasse.schuirmann@gmail.com
License: MIT
Platform: UNKNOWN
Requires-Dist: requests (~=2.13.0)
